utah_housing_stat386/__init__.py
utah_housing_stat386/cleaning.py
utah_housing_stat386/core.py
utah_housing_stat386/demo.py
utah_housing_stat386/streamlit_app.py
utah_housing_stat386/data/test_data.csv
utah_housing_stat386-0.3.4.dist-info/METADATA
utah_housing_stat386-0.3.4.dist-info/WHEEL
utah_housing_stat386-0.3.4.dist-info/licenses/LICENSE
utah_housing_stat386-0.3.4.dist-info/RECORD
