Metadata-Version: 2.4
Name: utah_housing_stat386
Version: 0.3.4
Summary: A package to scrape Utah housing data for certain cities of Salt Lake and Utah counties
Project-URL: Homepage, https://github.com/sethfrand/Stat_386_final_project
Project-URL: Repository, https://github.com/sethfrand/Stat_386_final_project.git
Project-URL: Issues, https://github.com/sethfrand/Stat_386_final_project/issues
Author: Seth Frandsen, Carson Ordyna
License: MIT
License-File: LICENSE
Classifier: License :: OSI Approved :: MIT License
Classifier: Operating System :: OS Independent
Classifier: Programming Language :: Python :: 3.11
Requires-Python: >=3.10
Requires-Dist: beautifulsoup4>=4.14.2
Requires-Dist: crawlee[playwright]>=1.1.0
Requires-Dist: matplotlib>=3.10.8
Requires-Dist: numpy>=2.3.5
Requires-Dist: pandas>=2.3.3
Requires-Dist: plotly>=6.5.0
Requires-Dist: psutil>=7.1.3
Requires-Dist: quarto>=0.1.0
Requires-Dist: requests>=2.32.5
Requires-Dist: scikit-learn>=1.8.0
Requires-Dist: statsmodels>=0.14.6
Requires-Dist: streamlit>=1.52.1
Provides-Extra: dev
Requires-Dist: pytest>=7.0.0; extra == 'dev'
Requires-Dist: streamlit>=1.52.1; extra == 'dev'
